pycounts_tb/__init__.py
pycounts_tb/data/__init__.py
pycounts_tb/data/flatland.txt
pycounts_tb/datasets.py
pycounts_tb/plotting.py
pycounts_tb/pycounts_tb.py
pycounts_tb-0.7.8.dist-info/LICENSE
pycounts_tb-0.7.8.dist-info/WHEEL
pycounts_tb-0.7.8.dist-info/METADATA
pycounts_tb-0.7.8.dist-info/RECORD
