Metadata-Version: 2.1
Name: pycounts-tb
Version: 0.7.8
Summary: Calculate words  in a text file!
License: MIT
Author: Tomas Beuzen
Requires-Python: >=3.9,<4.0
Classifier: License :: OSI Approved :: MIT License
Classifier: Programming Language :: Python :: 3
Classifier: Programming Language :: Python :: 3.10
Classifier: Programming Language :: Python :: 3.9
Requires-Dist: matplotlib (>=3.5.0,<4.0.0)
